aiida_icon/__init__.py
aiida_icon/_version.py
aiida_icon/builder.py
aiida_icon/calculations.py
aiida_icon/calcutils.py
aiida_icon/exceptions.py
aiida_icon/py.typed
aiida_icon/tools.py
aiida_icon/iconutils/__init__.py
aiida_icon/iconutils/masternml.py
aiida_icon/iconutils/modelnml.py
aiida_icon/iconutils/namelists.py
aiida_icon/site_support/__init__.py
aiida_icon/site_support/cscs/__init__.py
aiida_icon/site_support/cscs/alps.py
aiida_icon/site_support/cscs/santis.py
aiida_icon/site_support/cscs/todi.py
aiida_icon/site_support/cscs/wrapper_scripts/gh200_cpu.sh
aiida_icon/site_support/cscs/wrapper_scripts/todi_cpu.sh
aiida_icon/testing/__init__.py
aiida_icon/testing/mock_icon.py
aiida_icon-0.5.0.dist-info/METADATA
aiida_icon-0.5.0.dist-info/WHEEL
aiida_icon-0.5.0.dist-info/entry_points.txt
aiida_icon-0.5.0.dist-info/licenses/LICENSE
aiida_icon-0.5.0.dist-info/RECORD
