Metadata-Version: 2.4
Name: aiida-icon
Version: 0.5.0
Summary: AiiDA Plugin to run simulations with the ICON weather & climate model
Project-URL: Documentation, https://aiida-icon.github.io/aiida-icon/
Project-URL: Issues, https://github.com/DropD/aiida-icon/issues
Project-URL: Source, https://github.com/DropD/aiida-icon
Author-email: Rico Häuselmann <rico.haeuselmann@gmail.com>
License-Expression: MIT
License-File: LICENSE
Classifier: Development Status :: 4 - Beta
Classifier: Framework :: AiiDA
Classifier: Programming Language :: Python
Classifier: Programming Language :: Python :: 3.10
Classifier: Programming Language :: Python :: 3.11
Classifier: Programming Language :: Python :: 3.12
Classifier: Programming Language :: Python :: 3.13
Classifier: Programming Language :: Python :: Implementation :: CPython
Requires-Python: >=3.10
Requires-Dist: aiida-core>=2.5
Requires-Dist: click
Requires-Dist: f90nml
